<?xml version="1.0" encoding="utf-8" ?>
<root>
  <!--client说明：
  *   key:    表示客户端类型（1用户端，2商户端，4工作端）
  -->
  <!--adpage说明：
  *     id:     广告页ID
  *     name:   广告页名称
  -->
  <!--adposition说明：
  *     id:           广告位ID
  *     code:         广告编号
  *     name:         广告位名称
  *     maxcount:     最大广告数
  *     enable:       是否启用
  *     displaytype:  广告展示类型（1图片轮托播，2单图展示，4滑动跳过，8定时跳过）
  *     pic:          广告位在页图中的预览效果图
  *     intro:        广告位描述
  -->
  <client key="1" value="用户端">
    <adpage id="10201" name="首页(v1.2)">
      <adposition id="10201001" code="U01002_home001" name="顶部通栏Banner" maxcount="6" enable="true" displaytype="1" pic="/img1/advertposition/U01002_home001.png"  intro="一般为多个图片广告，自动滚动（或手动滑动）广告图可切换，点击后进入相应的内容页.尺寸标准为：720*320像素"></adposition>
      <adposition id="10201002" code="U01002_home002" name="中部横幅" maxcount="1" enable="true" displaytype="2" pic="/img1/advertposition/U01002_home002.png"  intro="一般为单个图片广告，点击后进入相应的内容页.尺寸标准为：680*340像素"></adposition>
      <adposition id="10201003" code="U01002_home003" name="中部左一按钮广告" maxcount="1" enable="true" displaytype="2" pic="/img1/advertposition/U01002_home003.png"  intro="一般为单个图片广告，点击后进入相应的内容页.尺寸标准为：332*332像素"></adposition>
      <adposition id="10201004" code="U01002_home004" name="中部右一按钮广告" maxcount="1" enable="true" displaytype="2" pic="/img1/advertposition/U01002_home004.png"  intro="一般为单个图片广告，点击后进入相应的内容页.尺寸标准为：332*332像素"></adposition>
      <adposition id="10201005" code="U01002_home005" name="底部横幅一" maxcount="1" enable="true" displaytype="2" pic="/img1/advertposition/U01002_home005.png"  intro="一般为单个图片广告，点击后进入相应的内容页.尺寸标准为：680*340像素"></adposition>
      <adposition id="10201006" code="U01002_home006" name="底部左一按钮广告" maxcount="1" enable="true" displaytype="2" pic="/img1/advertposition/U01002_home006.png"  intro="一般为单个图片广告，点击后进入相应的内容页.尺寸标准为：332*332像素"></adposition>
      <adposition id="10201007" code="U01002_home007" name="底部右一按钮广告" maxcount="1" enable="true" displaytype="2" pic="/img1/advertposition/U01002_home007.png"  intro="一般为单个图片广告，点击后进入相应的内容页.尺寸标准为：332*332像素"></adposition>
      <adposition id="10201008" code="U01002_home008" name="底部横幅二" maxcount="1" enable="true" displaytype="2" pic="/img1/advertposition/U01002_home008.png"  intro="一般为单个图片广告，点击后进入相应的内容页.尺寸标准为：680*340像素"></adposition>
    </adpage>
    <adpage id="10202" name="淘一淘之精选实惠(v1.2)">
      <adposition id="10202001" code="U01002_malljxsh001" name="顶部通栏Banner" maxcount="6" enable="true" displaytype="1" pic="/img1/advertposition/U01002_malljxsh001.png"  intro="一般为多个图片广告，自动滚动（或手动滑动）广告图可切换，点击后进入相应的内容页.尺寸标准为：720*320像素"></adposition>
      <adposition id="10202002" code="U01002_malljxsh002" name="中部横幅一" maxcount="1" enable="true" displaytype="2" pic="/img1/advertposition/U01002_malljxsh002.png"  intro="一般为单个图片广告，点击后进入相应的内容页.尺寸标准为：680*320像素"></adposition>
      <adposition id="10202003" code="U01002_malljxsh003" name="中部左一按钮广告" maxcount="1" enable="true" displaytype="2" pic="/img1/advertposition/U01002_malljxsh003.png"  intro="一般为单个图片广告，点击后进入相应的内容页.尺寸标准为：332*332像素"></adposition>
      <adposition id="10202004" code="U01002_malljxsh004" name="中部右一按钮广告" maxcount="1" enable="true" displaytype="2" pic="/img1/advertposition/U01002_malljxsh004.png"  intro="一般为单个图片广告，点击后进入相应的内容页.尺寸标准为：332*332像素"></adposition>
      <adposition id="10202005" code="U01002_malljxsh005" name="中部通栏二" maxcount="1" enable="true" displaytype="2" pic="/img1/advertposition/U01002_malljxsh005.png"  intro="一般为单个图片广告，点击后进入相应的内容页.尺寸标准为：680*320像素"></adposition>
    </adpage>
    <adpage id="10203" name="淘一淘之全心直营(v1.2)">
      <adposition id="10203001" code="U01002_mallqxzy001" name="顶部通栏Banner" maxcount="6" enable="true" displaytype="1" pic="/img1/advertposition/U01002_mallqxzy001.png"  intro="一般为多个图片广告，自动滚动（或手动滑动）广告图可切换，点击后进入相应的内容页.尺寸标准为：720*320像素"></adposition>
    </adpage>
    <adpage id="10204" name="淘一淘之限时抢购(v1.2)">
      <adposition id="10204001" code="U01002_mallxsqg001" name="顶部通栏Banner" maxcount="6" enable="true" displaytype="1" pic="/img1/advertposition/U01002_mallxsqg001.png"  intro="一般为多个图片广告，自动滚动（或手动滑动）广告图可切换，点击后进入相应的内容页.尺寸标准为：720*320像素"></adposition>
    </adpage>
    <adpage id="1006" name="兴趣社区首页">
      <adposition id="1006002" code="U01002_forumxqsq001" name="顶部通栏(v1.2)" maxcount="6" enable="true" displaytype="1" pic="/img1/advertposition/U01002forumxqsq001.png"  intro="一般为多个图片广告，自动滚动（或手动滑动）广告图可切换，点击后进入相应的内容页.尺寸标准为：720*320像素"></adposition>
    </adpage>
  </client>
</root>